test/__init__.py
test/test.py
zut_nlp_utils/Attention.py
zut_nlp_utils/Sequence.py
zut_nlp_utils/__init__.py
zut_nlp_utils/get_score.py
zut_nlp_utils/load_model_dict.py
zut_nlp_utils/model_init.py
zut_nlp_utils/read_dir.py
zut_nlp_utils/tokenizer.py
zut_nlp_utils-0.2.dist-info/METADATA
zut_nlp_utils-0.2.dist-info/WHEEL
zut_nlp_utils-0.2.dist-info/top_level.txt
zut_nlp_utils-0.2.dist-info/RECORD
