Metadata-Version: 2.1
Name: zut-nlp-utils
Version: 0.2
Summary: 自然语言处理常用的工具类,正在完善中....
Home-page: https://gitee.com/liuyu_1997/nlp-utils.git
Author: 刘宇
Author-email: 506610466@qq.com
License: UNKNOWN
Platform: UNKNOWN
